<?xml version="1.0" encoding="UTF-8"?>
<FDSNStationXML xmlns:ingv="https://raw.githubusercontent.com/FDSN/StationXML/master/fdsn-station.xsd" xmlns:xsi="http://www.w3.org/2001/XMLSchema-instance" xmlns="http://www.fdsn.org/xml/station/1" schemaVersion="1.2" xsi:schemaLocation="http://www.fdsn.org/xml/station/1 http://www.fdsn.org/xml/station/fdsn-station-1.2.xsd"><Source>eXistDB</Source><Sender>INGV-ONT</Sender><Module>INGV-ONT WEB SERVICE: fdsnws-station | version: 1.1.57</Module><ModuleURI>"/exist/apps/fdsn-station/fdsnws/station/1/query?
level=response
MN BNI -- BHE 2018-08-07T04:07:38.000000 2018-08-07T04:10:38.000000
MN BNI -- BHN 2018-08-07T04:07:38.000000 2018-08-07T04:10:38.000000
MN BNI -- BHZ 2018-08-07T04:07:38.000000 2018-08-07T04:10:38.000000"</ModuleURI><Created>2023-12-06T19:41:03.309</Created><Network code="MN" startDate="1988-01-01T00:00:00" restrictedStatus="open"><Description>Mediterranean Very Broadband Seismographic Network</Description><Identifier type="DOI">10.13127/SD/fBBBtDtd6q</Identifier><TotalNumberStations>36</TotalNumberStations><SelectedNumberStations>3</SelectedNumberStations><Station code="BNI" startDate="1988-04-30T00:00:00" restrictedStatus="open"><Latitude>45.052</Latitude><Longitude>6.678</Longitude><Elevation>1395</Elevation><Site><Name>Bardonecchia, Italy</Name></Site><CreationDate>1988-04-30T00:00:00</CreationDate><TotalNumberChannels>108</TotalNumberChannels><SelectedNumberChannels>1</SelectedNumberChannels><Channel code="BHE" startDate="2016-10-26T09:55:00" endDate="2023-11-25T23:59:59" restrictedStatus="open" locationCode=""><Latitude>45.052</Latitude><Longitude>6.678</Longitude><Elevation>1395</Elevation><Depth>50</Depth><Azimuth>90</Azimuth><Dip>0</Dip><SampleRate>100</SampleRate><ClockDrift>0</ClockDrift><Sensor><Description>STRECKEISEN STS-2-120S</Description></Sensor><DataLogger><Description>QUANTERRA Q330</Description></DataLogger><Response><InstrumentSensitivity><Value>1500</Value><Frequency>0.02</Frequency><InputUnits><Name>m/s</Name></InputUnits><OutputUnits><Name>count</Name></OutputUnits></InstrumentSensitivity><Stage number="1"><PolesZeros><InputUnits><Name>m/s</Name></InputUnits><OutputUnits><Name>V</Name></OutputUnits><PzTransferFunctionType>LAPLACE (RADIANS/SECOND)</PzTransferFunctionType><NormalizationFactor>59680600</NormalizationFactor><NormalizationFrequency>0.02</NormalizationFrequency><Zero number="0"><Real>0</Real><Imaginary>0</Imaginary></Zero><Zero number="1"><Real>0</Real><Imaginary>0</Imaginary></Zero><Pole number="0"><Real>-0.035647</Real><Imaginary>-0.036879</Imaginary></Pole><Pole number="1"><Real>-0.035647</Real><Imaginary>0.036879</Imaginary></Pole><Pole number="2"><Real>-251.33</Real><Imaginary>0</Imaginary></Pole><Pole number="3"><Real>-131.04</Real><Imaginary>-467.29</Imaginary></Pole><Pole number="4"><Real>-131.04</Real><Imaginary>467.29</Imaginary></Pole></PolesZeros><StageGain><Value>1500</Value><Frequency>0.02</Frequency></StageGain></Stage></Response></Channel></Station><Station code="BNI" startDate="1988-04-30T00:00:00" restrictedStatus="open"><Latitude>45.052</Latitude><Longitude>6.678</Longitude><Elevation>1395</Elevation><Site><Name>Bardonecchia, Italy</Name></Site><CreationDate>1988-04-30T00:00:00</CreationDate><TotalNumberChannels>108</TotalNumberChannels><SelectedNumberChannels>1</SelectedNumberChannels><Channel code="BHN" startDate="2016-10-26T09:55:00" endDate="2023-11-25T23:59:59" restrictedStatus="open" locationCode=""><Latitude>45.052</Latitude><Longitude>6.678</Longitude><Elevation>1395</Elevation><Depth>50</Depth><Azimuth>0</Azimuth><Dip>0</Dip><SampleRate>100</SampleRate><ClockDrift>0</ClockDrift><Sensor><Description>STRECKEISEN STS-2-120S</Description></Sensor><DataLogger><Description>QUANTERRA Q330</Description></DataLogger><Response><InstrumentSensitivity><Value>1500</Value><Frequency>0.02</Frequency><InputUnits><Name>m/s</Name></InputUnits><OutputUnits><Name>count</Name></OutputUnits></InstrumentSensitivity><Stage number="1"><PolesZeros><InputUnits><Name>m/s</Name></InputUnits><OutputUnits><Name>V</Name></OutputUnits><PzTransferFunctionType>LAPLACE (RADIANS/SECOND)</PzTransferFunctionType><NormalizationFactor>59680600</NormalizationFactor><NormalizationFrequency>0.02</NormalizationFrequency><Zero number="0"><Real>0</Real><Imaginary>0</Imaginary></Zero><Zero number="1"><Real>0</Real><Imaginary>0</Imaginary></Zero><Pole number="0"><Real>-0.035647</Real><Imaginary>-0.036879</Imaginary></Pole><Pole number="1"><Real>-0.035647</Real><Imaginary>0.036879</Imaginary></Pole><Pole number="2"><Real>-251.33</Real><Imaginary>0</Imaginary></Pole><Pole number="3"><Real>-131.04</Real><Imaginary>-467.29</Imaginary></Pole><Pole number="4"><Real>-131.04</Real><Imaginary>467.29</Imaginary></Pole></PolesZeros><StageGain><Value>1500</Value><Frequency>0.02</Frequency></StageGain></Stage></Response></Channel></Station><Station code="BNI" startDate="1988-04-30T00:00:00" restrictedStatus="open"><Latitude>45.052</Latitude><Longitude>6.678</Longitude><Elevation>1395</Elevation><Site><Name>Bardonecchia, Italy</Name></Site><CreationDate>1988-04-30T00:00:00</CreationDate><TotalNumberChannels>108</TotalNumberChannels><SelectedNumberChannels>1</SelectedNumberChannels><Channel code="BHZ" startDate="2016-10-26T09:55:00" endDate="2023-11-25T23:59:59" restrictedStatus="open" locationCode=""><Latitude>45.052</Latitude><Longitude>6.678</Longitude><Elevation>1395</Elevation><Depth>50</Depth><Azimuth>0</Azimuth><Dip>-90</Dip><SampleRate>100</SampleRate><ClockDrift>0</ClockDrift><Sensor><Description>STRECKEISEN STS-2-120S</Description></Sensor><DataLogger><Description>QUANTERRA Q330</Description></DataLogger><Response><InstrumentSensitivity><Value>1500</Value><Frequency>0.02</Frequency><InputUnits><Name>m/s</Name></InputUnits><OutputUnits><Name>count</Name></OutputUnits></InstrumentSensitivity><Stage number="1"><PolesZeros><InputUnits><Name>m/s</Name></InputUnits><OutputUnits><Name>V</Name></OutputUnits><PzTransferFunctionType>LAPLACE (RADIANS/SECOND)</PzTransferFunctionType><NormalizationFactor>59680600</NormalizationFactor><NormalizationFrequency>0.02</NormalizationFrequency><Zero number="0"><Real>0</Real><Imaginary>0</Imaginary></Zero><Zero number="1"><Real>0</Real><Imaginary>0</Imaginary></Zero><Pole number="0"><Real>-0.035647</Real><Imaginary>-0.036879</Imaginary></Pole><Pole number="1"><Real>-0.035647</Real><Imaginary>0.036879</Imaginary></Pole><Pole number="2"><Real>-251.33</Real><Imaginary>0</Imaginary></Pole><Pole number="3"><Real>-131.04</Real><Imaginary>-467.29</Imaginary></Pole><Pole number="4"><Real>-131.04</Real><Imaginary>467.29</Imaginary></Pole></PolesZeros><StageGain><Value>1500</Value><Frequency>0.02</Frequency></StageGain></Stage></Response></Channel></Station></Network></FDSNStationXML>