<?xml version="1.0" encoding="UTF-8"?>
<FDSNStationXML xmlns:ingv="https://raw.githubusercontent.com/FDSN/StationXML/master/fdsn-station.xsd" xmlns:xsi="http://www.w3.org/2001/XMLSchema-instance" xmlns="http://www.fdsn.org/xml/station/1" schemaVersion="1.2" xsi:schemaLocation="http://www.fdsn.org/xml/station/1 http://www.fdsn.org/xml/station/fdsn-station-1.2.xsd"><Source>eXistDB</Source><Sender>INGV-ONT</Sender><Module>INGV-ONT WEB SERVICE: fdsnws-station | version: 1.1.57</Module><ModuleURI>"/exist/apps/fdsn-station/fdsnws/station/1/query?
level=response
OX AGOR -- HHE 2017-02-21T09:35:26.000000 2017-02-21T09:38:26.000000
OX AGOR -- HHN 2017-02-21T09:35:26.000000 2017-02-21T09:38:26.000000
OX AGOR -- HHZ 2017-02-21T09:35:26.000000 2017-02-21T09:38:26.000000"</ModuleURI><Created>2023-12-06T20:54:56.497</Created><Network code="OX" startDate="2016-01-01T00:00:00" restrictedStatus="open"><Description>North-East Italy Seismic Network</Description><TotalNumberStations>19</TotalNumberStations><SelectedNumberStations>3</SelectedNumberStations><Station code="AGOR" startDate="2016-01-01T00:00:00" restrictedStatus="open"><Latitude>46.2829</Latitude><Longitude>12.0472</Longitude><Elevation>631</Elevation><Site><Name>Agordo, Italy</Name></Site><CreationDate>2007-01-06T00:00:00</CreationDate><TotalNumberChannels>6</TotalNumberChannels><SelectedNumberChannels>1</SelectedNumberChannels><Channel code="HHE" startDate="2016-01-01T00:00:00" restrictedStatus="open" locationCode=""><Latitude>46.2329</Latitude><Longitude>12.0472</Longitude><Elevation>631</Elevation><Depth>0</Depth><Azimuth>90</Azimuth><Dip>0</Dip><SampleRate>80</SampleRate><ClockDrift>0</ClockDrift><Sensor><Description>STRECKEISEN STS-2-120S</Description></Sensor><DataLogger><Description>QUANTERRA Q680</Description></DataLogger><Response><InstrumentSensitivity><Value>589622000</Value><Frequency>0.02</Frequency><InputUnits><Name>m/s</Name></InputUnits><OutputUnits><Name>count</Name></OutputUnits></InstrumentSensitivity><Stage number="1"><PolesZeros><InputUnits><Name>m/s</Name></InputUnits><OutputUnits><Name>V</Name></OutputUnits><PzTransferFunctionType>LAPLACE (RADIANS/SECOND)</PzTransferFunctionType><NormalizationFactor>59680600</NormalizationFactor><NormalizationFrequency>0.02</NormalizationFrequency><Zero number="0"><Real>0</Real><Imaginary>0</Imaginary></Zero><Zero number="1"><Real>0</Real><Imaginary>0</Imaginary></Zero><Pole number="0"><Real>-0.035647</Real><Imaginary>-0.036879</Imaginary></Pole><Pole number="1"><Real>-0.035647</Real><Imaginary>0.036879</Imaginary></Pole><Pole number="2"><Real>-251.33</Real><Imaginary>0</Imaginary></Pole><Pole number="3"><Real>-131.04</Real><Imaginary>-467.29</Imaginary></Pole><Pole number="4"><Real>-131.04</Real><Imaginary>467.29</Imaginary></Pole></PolesZeros><StageGain><Value>1422.42</Value><Frequency>0.02</Frequency></StageGain></Stage><Stage number="2"><Coefficients><InputUnits><Name>V</Name></InputUnits><OutputUnits><Name>count</Name></OutputUnits><CfTransferFunctionType>DIGITAL</CfTransferFunctionType></Coefficients><Decimation><InputSampleRate>0</InputSampleRate><Factor>1</Factor><Offset>0</Offset><Delay>0</Delay><Correction>0</Correction></Decimation><StageGain><Value>414520</Value><Frequency>0</Frequency></StageGain></Stage></Response></Channel></Station><Station code="AGOR" startDate="2016-01-01T00:00:00" restrictedStatus="open"><Latitude>46.2829</Latitude><Longitude>12.0472</Longitude><Elevation>631</Elevation><Site><Name>Agordo, Italy</Name></Site><CreationDate>2007-01-06T00:00:00</CreationDate><TotalNumberChannels>6</TotalNumberChannels><SelectedNumberChannels>1</SelectedNumberChannels><Channel code="HHN" startDate="2016-01-01T00:00:00" restrictedStatus="open" locationCode=""><Latitude>46.2329</Latitude><Longitude>12.0472</Longitude><Elevation>631</Elevation><Depth>0</Depth><Azimuth>0</Azimuth><Dip>0</Dip><SampleRate>80</SampleRate><ClockDrift>0</ClockDrift><Sensor><Description>STRECKEISEN STS-2-120S</Description></Sensor><DataLogger><Description>QUANTERRA Q680</Description></DataLogger><Response><InstrumentSensitivity><Value>589622000</Value><Frequency>0.02</Frequency><InputUnits><Name>m/s</Name></InputUnits><OutputUnits><Name>count</Name></OutputUnits></InstrumentSensitivity><Stage number="1"><PolesZeros><InputUnits><Name>m/s</Name></InputUnits><OutputUnits><Name>V</Name></OutputUnits><PzTransferFunctionType>LAPLACE (RADIANS/SECOND)</PzTransferFunctionType><NormalizationFactor>59680600</NormalizationFactor><NormalizationFrequency>0.02</NormalizationFrequency><Zero number="0"><Real>0</Real><Imaginary>0</Imaginary></Zero><Zero number="1"><Real>0</Real><Imaginary>0</Imaginary></Zero><Pole number="0"><Real>-0.035647</Real><Imaginary>-0.036879</Imaginary></Pole><Pole number="1"><Real>-0.035647</Real><Imaginary>0.036879</Imaginary></Pole><Pole number="2"><Real>-251.33</Real><Imaginary>0</Imaginary></Pole><Pole number="3"><Real>-131.04</Real><Imaginary>-467.29</Imaginary></Pole><Pole number="4"><Real>-131.04</Real><Imaginary>467.29</Imaginary></Pole></PolesZeros><StageGain><Value>1422.42</Value><Frequency>0.02</Frequency></StageGain></Stage><Stage number="2"><Coefficients><InputUnits><Name>V</Name></InputUnits><OutputUnits><Name>count</Name></OutputUnits><CfTransferFunctionType>DIGITAL</CfTransferFunctionType></Coefficients><Decimation><InputSampleRate>0</InputSampleRate><Factor>1</Factor><Offset>0</Offset><Delay>0</Delay><Correction>0</Correction></Decimation><StageGain><Value>414520</Value><Frequency>0</Frequency></StageGain></Stage></Response></Channel></Station><Station code="AGOR" startDate="2016-01-01T00:00:00" restrictedStatus="open"><Latitude>46.2829</Latitude><Longitude>12.0472</Longitude><Elevation>631</Elevation><Site><Name>Agordo, Italy</Name></Site><CreationDate>2007-01-06T00:00:00</CreationDate><TotalNumberChannels>6</TotalNumberChannels><SelectedNumberChannels>1</SelectedNumberChannels><Channel code="HHZ" startDate="2016-01-01T00:00:00" restrictedStatus="open" locationCode=""><Latitude>46.2329</Latitude><Longitude>12.0472</Longitude><Elevation>631</Elevation><Depth>0</Depth><Azimuth>0</Azimuth><Dip>-90</Dip><SampleRate>80</SampleRate><ClockDrift>0</ClockDrift><Sensor><Description>STRECKEISEN STS-2-120S</Description></Sensor><DataLogger><Description>QUANTERRA Q680</Description></DataLogger><Response><InstrumentSensitivity><Value>589622000</Value><Frequency>0.02</Frequency><InputUnits><Name>m/s</Name></InputUnits><OutputUnits><Name>count</Name></OutputUnits></InstrumentSensitivity><Stage number="1"><PolesZeros><InputUnits><Name>m/s</Name></InputUnits><OutputUnits><Name>V</Name></OutputUnits><PzTransferFunctionType>LAPLACE (RADIANS/SECOND)</PzTransferFunctionType><NormalizationFactor>59680600</NormalizationFactor><NormalizationFrequency>0.02</NormalizationFrequency><Zero number="0"><Real>0</Real><Imaginary>0</Imaginary></Zero><Zero number="1"><Real>0</Real><Imaginary>0</Imaginary></Zero><Pole number="0"><Real>-0.035647</Real><Imaginary>-0.036879</Imaginary></Pole><Pole number="1"><Real>-0.035647</Real><Imaginary>0.036879</Imaginary></Pole><Pole number="2"><Real>-251.33</Real><Imaginary>0</Imaginary></Pole><Pole number="3"><Real>-131.04</Real><Imaginary>-467.29</Imaginary></Pole><Pole number="4"><Real>-131.04</Real><Imaginary>467.29</Imaginary></Pole></PolesZeros><StageGain><Value>1422.42</Value><Frequency>0.02</Frequency></StageGain></Stage><Stage number="2"><Coefficients><InputUnits><Name>V</Name></InputUnits><OutputUnits><Name>count</Name></OutputUnits><CfTransferFunctionType>DIGITAL</CfTransferFunctionType></Coefficients><Decimation><InputSampleRate>0</InputSampleRate><Factor>1</Factor><Offset>0</Offset><Delay>0</Delay><Correction>0</Correction></Decimation><StageGain><Value>414520</Value><Frequency>0</Frequency></StageGain></Stage></Response></Channel></Station></Network></FDSNStationXML>